processing/__init__.py
processing/combinacao.py
processing/transformacao.py
utils/__init__.py
utils/io.py
utils/plot.py
gerdison_imagem_processo-0.0.1.dist-info/METADATA
gerdison_imagem_processo-0.0.1.dist-info/WHEEL
gerdison_imagem_processo-0.0.1.dist-info/top_level.txt
gerdison_imagem_processo-0.0.1.dist-info/RECORD
