Metadata-Version: 2.1
Name: gerdison-imagem-processo
Version: 0.0.1
Summary: Pacote de Processamento de imagens
Author: Gerdison
Author-email: gerdison.dona@gmail.com
Requires-Python: >=3.8
Requires-Dist: numpy
Requires-Dist: scikit-image (>=0.16.1)
Requires-Dist: matplotlib
